rockfinder/.DS_Store
rockfinder/__init__.py
rockfinder/__version__.py
rockfinder/cl_utils.py
rockfinder/default_settings.yaml
rockfinder/jpl_horizons_ephemeris.py
rockfinder/orbfit_ephemeris.py
rockfinder/utKit.py
rockfinder/bin/activate
rockfinder/bin/conda
rockfinder/bin/deactivate
rockfinder/commonutils/__init__.py
rockfinder/commonutils/getpackagepath.py
rockfinder/tests/__init__.py
rockfinder/tests/test_jpl_horizons_ephemeris.py
rockfinder/tests/test_orbfit_ephemeris.py
rockfinder/tests/input/astorb-partial.dat
rockfinder/tests/input/example_settings.yaml
rockfinder/tests/output/astorb-partial.dat
rockfinder/tests/output/example_settings.yaml
rockfinder-0.6.1.dist-info/DESCRIPTION.rst
rockfinder-0.6.1.dist-info/METADATA
rockfinder-0.6.1.dist-info/RECORD
rockfinder-0.6.1.dist-info/WHEEL
rockfinder-0.6.1.dist-info/entry_points.txt
rockfinder-0.6.1.dist-info/metadata.json
rockfinder-0.6.1.dist-info/top_level.txt
