Metadata-Version: 2.0
Name: rockfinder
Version: 0.6.1
Summary: A python package and command-line tools to A python package and command-line suite to generate solar-system body ephemerides and to determine if specific transient dections are in fact known asteroids
Home-page: https://github.com/thespacedoctor/rockfinder
Author: David Young
Author-email: davidrobertyoung@gmail.com
License: MIT
Download-URL: https://github.com/thespacedoctor/rockfinder/archive/v0.6.1.zip
Keywords: asteroid, ephemeris, astronomy,solar-system, command-line
Platform: UNKNOWN
Classifier: Development Status :: 4 - Beta
Classifier: License :: OSI Approved :: MIT License
Classifier: Programming Language :: Python :: 2.7
Classifier: Topic :: Utilities
Requires-Dist: fundamentals
Requires-Dist: grequests
Requires-Dist: ndg-httpsclient
Requires-Dist: psutil
Requires-Dist: pyyaml
Requires-Dist: rockfinder
